{
  "@context": {
    "@language": "en",
    "@vocab": "https://schema.org/",
    "citeAs": "cr:citeAs",
    "column": "cr:column",
    "conformsTo": "dct:conformsTo",
    "cr": "http://mlcommons.org/croissant/",
    "data": {
      "@id": "cr:data",
      "@type": "@json"
    },
    "dataType": {
      "@id": "cr:dataType",
      "@type": "@vocab"
    },
    "dct": "http://purl.org/dc/terms/",
    "extract": "cr:extract",
    "field": "cr:field",
    "fileObject": "cr:fileObject",
    "fileProperty": "cr:fileProperty",
    "fileSet": "cr:fileSet",
    "format": "cr:format",
    "includes": "cr:includes",
    "isLiveDataset": "cr:isLiveDataset",
    "jsonPath": "cr:jsonPath",
    "key": "cr:key",
    "md5": "cr:md5",
    "parentField": "cr:parentField",
    "path": "cr:path",
    "recordSet": "cr:recordSet",
    "references": "cr:references",
    "regex": "cr:regex",
    "repeated": "cr:repeated",
    "replace": "cr:replace",
    "sc": "https://schema.org/",
    "separator": "cr:separator",
    "source": "cr:source",
    "subField": "cr:subField",
    "transform": "cr:transform"
  },
  "@type": "sc:Dataset",
  "conformsTo": "http://mlcommons.org/croissant/1.0",
  "name": "ds004579",
  "alternateName": [
    "DS004579"
  ],
  "description": "Interval Timing Task. eeg dataset accessible via EEGDash as `DS004579` with standardized BIDS metadata.",
  "url": "https://eegdash.org/api/dataset/eegdash.dataset.DS004579.html",
  "keywords": [
    "EEG",
    "BIDS",
    "neuroscience",
    "Visual",
    "Parkinson's",
    "Decision-making"
  ],
  "isAccessibleForFree": true,
  "includedInDataCatalog": {
    "@type": "sc:DataCatalog",
    "name": "EEG Dash",
    "url": "https://eegdash.org/"
  },
  "license": "https://creativecommons.org/publicdomain/zero/1.0/",
  "creator": [
    {
      "@type": "sc:Person",
      "name": "Arun Singh arun.singh@usd.edu"
    },
    {
      "@type": "sc:Person",
      "name": "Rachel Cole rachel-cole@uiowa.edu"
    },
    {
      "@type": "sc:Person",
      "name": "Arturo Espinoza arturo-espinoza@uiowa.edu"
    },
    {
      "@type": "sc:Person",
      "name": "Jan R Wessel jan-wessel@uiowa.edu"
    },
    {
      "@type": "sc:Person",
      "name": "Jim Cavanagh jcavanagh@unm.edu"
    },
    {
      "@type": "sc:Person",
      "name": "Nandakumar Narayanan nandakumar-narayanan@uiowa.edu"
    }
  ],
  "editor": {
    "@type": "sc:Person",
    "name": "Nandakumar Narayanan nandakumar-narayanan@uiowa.edu"
  },
  "datePublished": "2023",
  "identifier": "doi:10.18112/openneuro.ds004579.v1.0.0",
  "sameAs": [
    "https://doi.org/10.18112/openneuro.ds004579.v1.0.0",
    "https://openneuro.org/datasets/ds004579",
    "https://huggingface.co/datasets/EEGDash/ds004579"
  ],
  "citeAs": "Arun Singh arun.singh@usd.edu, Rachel Cole rachel-cole@uiowa.edu, Arturo Espinoza arturo-espinoza@uiowa.edu, Jan R Wessel jan-wessel@uiowa.edu, Jim Cavanagh jcavanagh@unm.edu (2023). Interval Timing Task. doi:10.18112/openneuro.ds004579.v1.0.0",
  "version": "v1.2.1",
  "dateCreated": "2023-05-25",
  "dateModified": "2023-05-25",
  "measurementTechnique": [
    "BIDS task: IntervalTiming"
  ],
  "maintainer": [
    {
      "@type": "sc:Person",
      "name": "Nandakumar Narayanan"
    }
  ],
  "distribution": [
    {
      "@type": "cr:FileObject",
      "@id": "ds004579-bids-bucket",
      "name": "ds004579 BIDS bucket",
      "description": "Canonical BIDS-formatted dataset bucket for DS004579.",
      "contentUrl": "s3://openneuro.org/ds004579",
      "encodingFormat": "application/vnd.bids+directory"
    },
    {
      "@type": "cr:FileObject",
      "@id": "ds004579-openneuro",
      "name": "ds004579 on OpenNeuro",
      "description": "OpenNeuro dataset landing page.",
      "contentUrl": "https://openneuro.org/datasets/ds004579",
      "encodingFormat": "text/html"
    },
    {
      "@type": "cr:FileObject",
      "@id": "ds004579-eegdash-records",
      "name": "ds004579 EEGDash records (live)",
      "description": "Live JSON listing of every recording in this dataset, with BIDS metadata, channel counts, and S3 storage keys.",
      "contentUrl": "https://data.eegdash.org/api/eegdash/records?filter=%7B%22dataset%22%3A%22ds004579%22%7D",
      "encodingFormat": "application/json",
      "isLiveDataset": true
    },
    {
      "@type": "cr:FileObject",
      "@id": "ds004579-nemar",
      "name": "ds004579 on NeMAR",
      "description": "NEMAR dataset landing page with pipeline plots.",
      "contentUrl": "https://nemar.org/dataexplorer/detail?dataset_id=ds004579",
      "encodingFormat": "text/html"
    },
    {
      "@type": "cr:FileObject",
      "@id": "ds004579-huggingface",
      "name": "EEGDash/ds004579 on Hugging Face",
      "description": "Hugging Face dataset mirror — ready for `datasets.load_dataset(...)` pulls.",
      "contentUrl": "https://huggingface.co/datasets/EEGDash/ds004579",
      "encodingFormat": "application/vnd.huggingface-dataset+json"
    }
  ]
}