{
  "@context": {
    "@language": "en",
    "@vocab": "https://schema.org/",
    "citeAs": "cr:citeAs",
    "column": "cr:column",
    "conformsTo": "dct:conformsTo",
    "cr": "http://mlcommons.org/croissant/",
    "data": {
      "@id": "cr:data",
      "@type": "@json"
    },
    "dataType": {
      "@id": "cr:dataType",
      "@type": "@vocab"
    },
    "dct": "http://purl.org/dc/terms/",
    "extract": "cr:extract",
    "field": "cr:field",
    "fileObject": "cr:fileObject",
    "fileProperty": "cr:fileProperty",
    "fileSet": "cr:fileSet",
    "format": "cr:format",
    "includes": "cr:includes",
    "isLiveDataset": "cr:isLiveDataset",
    "jsonPath": "cr:jsonPath",
    "key": "cr:key",
    "md5": "cr:md5",
    "parentField": "cr:parentField",
    "path": "cr:path",
    "recordSet": "cr:recordSet",
    "references": "cr:references",
    "regex": "cr:regex",
    "repeated": "cr:repeated",
    "replace": "cr:replace",
    "sc": "https://schema.org/",
    "separator": "cr:separator",
    "source": "cr:source",
    "subField": "cr:subField",
    "transform": "cr:transform"
  },
  "@type": "sc:Dataset",
  "conformsTo": "http://mlcommons.org/croissant/1.0",
  "name": "ds005953",
  "alternateName": [
    "DS005953"
  ],
  "description": "iEEG_visual. ieeg dataset accessible via EEGDash as `DS005953` with standardized BIDS metadata.",
  "url": "https://eegdash.org/api/dataset/eegdash.dataset.DS005953.html",
  "keywords": [
    "EEG",
    "BIDS",
    "neuroscience",
    "IEEG",
    "['Visual']",
    "['Surgery']",
    "['Perception']"
  ],
  "isAccessibleForFree": true,
  "includedInDataCatalog": {
    "@type": "sc:DataCatalog",
    "name": "EEG Dash",
    "url": "https://eegdash.org/"
  },
  "license": "https://creativecommons.org/publicdomain/zero/1.0/",
  "creator": [
    {
      "@type": "sc:Person",
      "name": "Jonathan Winawer"
    },
    {
      "@type": "sc:Person",
      "name": "Dora Hermes"
    }
  ],
  "funder": [
    {
      "@type": "sc:Organization",
      "name": "This research has received funding from the National Institute Of Mental Health of the National Institutes of Health under Award Number R01MH111417"
    }
  ],
  "datePublished": "2015",
  "identifier": "doi:10.18112/openneuro.ds005953.v1.0.0",
  "sameAs": [
    "https://doi.org/10.18112/openneuro.ds005953.v1.0.0",
    "https://openneuro.org/datasets/ds005953",
    "https://huggingface.co/datasets/EEGDash/ds005953"
  ],
  "citeAs": "Jonathan Winawer, Dora Hermes (2015). iEEG_visual. doi:10.18112/openneuro.ds005953.v1.0.0",
  "version": "1.0.2",
  "measurementTechnique": [
    "BIDS task: visual"
  ],
  "distribution": [
    {
      "@type": "cr:FileObject",
      "@id": "ds005953-bids-bucket",
      "name": "ds005953 BIDS bucket",
      "description": "Canonical BIDS-formatted dataset bucket for DS005953.",
      "contentUrl": "s3://openneuro.org/ds005953",
      "encodingFormat": "application/vnd.bids+directory",
      "sha256": "main"
    },
    {
      "@type": "cr:FileObject",
      "@id": "ds005953-openneuro",
      "name": "ds005953 on OpenNeuro",
      "description": "OpenNeuro dataset landing page.",
      "contentUrl": "https://openneuro.org/datasets/ds005953",
      "encodingFormat": "text/html",
      "sha256": "main"
    },
    {
      "@type": "cr:FileObject",
      "@id": "ds005953-eegdash-records",
      "name": "ds005953 EEGDash records (live)",
      "description": "Live JSON listing of every recording in this dataset, with BIDS metadata, channel counts, and S3 storage keys.",
      "contentUrl": "https://data.eegdash.org/api/eegdash/records?filter=%7B%22dataset%22%3A%22ds005953%22%7D",
      "encodingFormat": "application/json",
      "isLiveDataset": true,
      "sha256": "main"
    },
    {
      "@type": "cr:FileObject",
      "@id": "ds005953-nemar",
      "name": "ds005953 on NeMAR",
      "description": "NEMAR dataset landing page with pipeline plots.",
      "contentUrl": "https://nemar.org/dataexplorer/detail?dataset_id=ds005953",
      "encodingFormat": "text/html",
      "sha256": "main"
    },
    {
      "@type": "cr:FileObject",
      "@id": "ds005953-huggingface",
      "name": "EEGDash/ds005953 on Hugging Face",
      "description": "Hugging Face dataset mirror — ready for `datasets.load_dataset(...)` pulls.",
      "contentUrl": "https://huggingface.co/datasets/EEGDash/ds005953",
      "encodingFormat": "application/vnd.huggingface-dataset+json",
      "sha256": "main"
    }
  ]
}