{"openneuro": {"ds001785": ["eeg"], "ds001787": ["eeg"], "ds001810": ["eeg"], "ds001849": ["eeg"], "ds001971": ["eeg"], "ds002034": ["eeg"], "ds002094": ["eeg"], "ds002158": ["eeg"], "ds002181": ["eeg"], "ds002218": ["eeg"], "ds002336": ["eeg"], "ds002338": ["eeg"], "ds002578": ["eeg"], "ds002680": ["eeg"], "ds002691": ["eeg"], "ds002718": ["eeg"], "ds002720": ["eeg"], "ds002721": ["eeg"], "ds002722": ["eeg"], "ds002723": ["eeg"], "ds002724": ["eeg"], "ds002725": ["eeg"], "ds002778": ["eeg"], "ds002791": ["eeg"], "ds002814": ["eeg"], "ds002833": ["eeg"], "ds002893": ["eeg"], "ds003004": ["eeg"], "ds003039": ["eeg"], "ds003061": ["eeg"], "ds003190": ["eeg"], "ds003194": ["eeg"], "ds003195": ["eeg"], "ds003343": ["eeg"], "ds003380": ["eeg"], "ds003420": ["eeg"], "ds003421": ["eeg"], "ds003458": ["eeg"], "ds003474": ["eeg"], "ds003478": ["eeg"], "ds003490": ["eeg"], "ds003505": ["eeg"], "ds003506": ["eeg"], "ds003509": ["eeg"], "ds003516": ["eeg"], "ds003517": ["eeg"], "ds003518": ["eeg"], "ds003519": ["eeg"], "ds003522": ["eeg"], "ds003523": ["eeg"], "ds003555": ["eeg"], "ds003570": ["eeg"], "ds003574": ["eeg"], "ds003602": ["eeg"], "ds003620": ["eeg"], "ds003626": ["eeg"], "ds003638": ["eeg"], "ds003645": ["eeg", "meg"], "ds003655": ["eeg"], "ds003670": ["eeg"], "ds003690": ["eeg"], "ds003702": ["eeg"], "ds003710": ["eeg"], "ds003739": ["eeg"], "ds003751": ["eeg"], "ds003753": ["eeg"], "ds003766": ["eeg"], "ds003768": ["eeg"], "ds003774": ["eeg"], "ds003775": ["eeg"], "ds003800": ["eeg"], "ds003801": ["eeg"], "ds003805": ["eeg"], "ds003810": ["eeg"], "ds003822": ["eeg"], "ds003825": ["eeg"], "ds003838": ["eeg"], "ds003846": ["eeg"], "ds003885": ["eeg"], "ds003887": ["eeg"], "ds003944": ["eeg"], "ds003947": ["eeg"], "ds003969": ["eeg"], "ds003987": ["eeg"], "ds004000": ["eeg"], "ds004010": ["eeg"], "ds004015": ["eeg"], "ds004017": ["eeg"], "ds004018": ["eeg"], "ds004019": ["eeg"], "ds004022": ["eeg"], "ds004024": ["eeg"], "ds004033": ["eeg"], "ds004040": ["eeg"], "ds004043": ["eeg"], "ds004067": ["eeg"], "ds004075": ["eeg"], "ds004105": ["eeg"], "ds004106": ["eeg"], "ds004117": ["eeg"], "ds004118": ["eeg"], "ds004119": ["eeg"], "ds004120": ["eeg"], "ds004121": ["eeg"], "ds004122": ["eeg"], "ds004123": ["eeg"], "ds004147": ["eeg"], "ds004148": ["eeg"], "ds004151": ["eeg"], "ds004152": ["eeg"], "ds004166": ["eeg"], "ds004196": ["eeg"], "ds004200": ["eeg"], "ds004252": ["eeg"], "ds004256": ["eeg"], "ds004262": ["eeg"], "ds004264": ["eeg"], "ds004279": ["eeg"], "ds004284": ["eeg"], "ds004295": ["eeg"], "ds004306": ["eeg"], "ds004315": ["eeg"], "ds004317": ["eeg"], "ds004324": ["eeg"], "ds004347": ["eeg"], "ds004348": ["eeg"], "ds004350": ["eeg"], "ds004356": ["eeg"], "ds004357": ["eeg"], "ds004362": ["eeg"], "ds004367": ["eeg"], "ds004368": ["eeg"], "ds004369": ["eeg"], "ds004381": ["eeg"], "ds004388": ["eeg"], "ds004389": ["eeg"], "ds004395": ["eeg"], "ds004408": ["eeg"], "ds004444": ["eeg"], "ds004446": ["eeg"], "ds004447": ["eeg"], "ds004448": ["eeg"], "ds004460": ["eeg"], "ds004475": ["eeg"], "ds004477": ["eeg"], "ds004502": ["eeg"], "ds004504": ["eeg"], "ds004505": ["eeg"], "ds004511": ["eeg"], "ds004514": ["eeg", "nirs"], "ds004515": ["eeg"], "ds004517": ["eeg"], "ds004519": ["eeg"], "ds004520": ["eeg"], "ds004521": ["eeg"], "ds004532": ["eeg"], "ds004541": ["eeg", "nirs"], "ds004554": ["eeg"], "ds004561": ["eeg"], "ds004563": ["eeg"], "ds004572": ["eeg"], "ds004574": ["eeg"], "ds004577": ["eeg"], "ds004579": ["eeg"], "ds004580": ["eeg"], "ds004582": ["eeg"], "ds004584": ["eeg"], "ds004587": ["eeg"], "ds004588": ["eeg"], "ds004595": ["eeg"], "ds004598": ["eeg"], "ds004602": ["eeg"], "ds004603": ["eeg"], "ds004621": ["eeg"], "ds004625": ["eeg"], "ds004626": ["eeg"], "ds004635": ["eeg"], "ds004657": ["eeg"], "ds004660": ["eeg"], "ds004661": ["eeg"], "ds004706": ["eeg"], "ds004718": ["eeg"], "ds004745": ["eeg"], "ds004752": ["eeg", "ieeg"], "ds004771": ["eeg"], "ds004784": ["eeg"], "ds004785": ["eeg"], "ds004796": ["eeg"], "ds004802": ["eeg"], "ds004816": ["eeg"], "ds004817": ["eeg"], "ds004840": ["eeg"], "ds004841": ["eeg"], "ds004842": ["eeg"], "ds004843": ["eeg"], "ds004844": ["eeg"], "ds004849": ["eeg"], "ds004850": ["eeg"], "ds004851": ["eeg"], "ds004852": ["eeg"], "ds004853": ["eeg"], "ds004854": ["eeg"], "ds004855": ["eeg"], "ds004860": ["eeg"], "ds004883": ["eeg"], "ds004902": ["eeg"], "ds004917": ["eeg"], "ds004940": ["eeg"], "ds004942": ["eeg"], "ds004951": ["eeg"], "ds004952": ["eeg"], "ds004980": ["eeg"], "ds004995": ["eeg"], "ds005021": ["eeg"], "ds005028": ["eeg"], "ds005034": ["eeg"], "ds005048": ["eeg"], "ds005079": ["eeg"], "ds005087": ["eeg"], "ds005089": ["eeg"], "ds005095": ["eeg"], "ds005106": ["eeg"], "ds005114": ["eeg"], "ds005121": ["eeg"], "ds005131": ["eeg"], "ds005170": ["eeg"], "ds005178": ["eeg"], "ds005185": ["eeg"], "ds005189": ["eeg"], "ds005207": ["eeg"], "ds005262": ["eeg"], "ds005273": ["eeg"], "ds005274": ["eeg"], "ds005280": ["eeg"], "ds005284": ["eeg"], "ds005285": ["eeg"], "ds005286": ["eeg"], "ds005289": ["eeg"], "ds005291": ["eeg"], "ds005292": ["eeg"], "ds005293": ["eeg"], "ds005296": ["eeg"], "ds005305": ["eeg"], "ds005307": ["eeg"], "ds005340": ["eeg"], "ds005342": ["eeg"], "ds005343": ["eeg"], "ds005345": ["eeg"], "ds005363": ["eeg"], "ds005383": ["eeg"], "ds005385": ["eeg"], "ds005397": ["eeg"], "ds005403": ["eeg"], "ds005406": ["eeg"], "ds005408": ["eeg"], "ds005410": ["eeg"], "ds005416": ["eeg"], "ds005420": ["eeg"], "ds005429": ["eeg"], "ds005473": ["eeg"], "ds005486": ["eeg"], "ds005505": ["eeg"], "ds005506": ["eeg"], "ds005507": ["eeg"], "ds005508": ["eeg"], "ds005509": ["eeg"], "ds005510": ["eeg"], "ds005512": ["eeg"], "ds005514": ["eeg"], "ds005515": ["eeg"], "ds005516": ["eeg"], "ds005520": ["eeg"], "ds005530": ["eeg"], "ds005540": ["eeg"], "ds005555": ["eeg"], "ds005565": ["eeg"], "ds005571": ["eeg"], "ds005586": ["eeg"], "ds005594": ["eeg"], "ds005620": ["eeg"], "ds005628": ["eeg"], "ds005642": ["eeg"], "ds005648": ["eeg"], "ds005662": ["eeg"], "ds005672": ["eeg"], "ds005688": ["eeg"], "ds005692": ["eeg"], "ds005697": ["eeg"], "ds005779": ["eeg"], "ds005795": ["eeg"], "ds005811": ["eeg"], "ds005815": ["eeg"], "ds005841": ["eeg"], "ds005857": ["eeg"], "ds005863": ["eeg"], "ds005866": ["eeg"], "ds005868": ["eeg"], "ds005872": ["eeg"], "ds005873": ["eeg"], "ds005876": ["eeg"], "ds005907": ["eeg"], "ds005932": ["eeg"], "ds005946": ["eeg"], "ds005960": ["eeg"], "ds006018": ["eeg"], "ds006033": ["eeg"], "ds006036": ["eeg"], "ds006040": ["eeg"], "ds006095": ["eeg"], "ds006104": ["eeg"], "ds006110": ["eeg"], "ds006126": ["eeg"], "ds006142": ["eeg"], "ds006159": ["eeg"], "ds006171": ["eeg"], "ds006222": ["eeg"], "ds006260": ["eeg"], "ds006269": ["eeg"], "ds006317": ["eeg"], "ds006366": ["eeg"], "ds006367": ["eeg"], "ds006370": ["eeg"], "ds006374": ["eeg"], "ds006386": ["eeg"], "ds006394": ["eeg"], "ds006434": ["eeg"], "ds006437": ["eeg"], "ds006446": ["eeg"], "ds006465": ["eeg"], "ds006466": ["eeg"], "ds006480": ["eeg"], "ds006525": ["eeg"], "ds006547": ["eeg"], "ds006554": ["eeg"], "ds006563": ["eeg"], "ds006576": ["eeg"], "ds006593": ["eeg"], "ds006647": ["eeg"], "ds006648": ["eeg"], "ds006695": ["eeg"], "ds006735": ["eeg"], "ds006761": ["eeg"], "ds006768": ["eeg"], "ds006801": ["eeg"], "ds006802": ["eeg"], "ds006803": ["eeg"], "ds006817": ["eeg"], "ds006839": ["eeg"], "ds006840": ["eeg"], "ds006848": ["eeg"], "ds006850": ["eeg"], "ds006861": ["eeg"], "ds006866": ["eeg"], "ds006897": ["eeg"], "ds006921": ["eeg"], "ds006923": ["eeg"], "ds006945": ["eeg"], "ds006963": ["eeg"], "ds006979": ["eeg"], "ds007006": ["eeg"], "ds007012": ["eeg"], "ds007020": ["eeg"], "ds007028": ["eeg"], "ds007052": ["eeg"], "ds007056": ["eeg"], "ds007069": ["eeg"], "ds007081": ["eeg"], "ds007096": ["eeg"], "ds007137": ["eeg"], "ds007139": ["eeg"], "ds007162": ["eeg"], "ds007169": ["eeg"], "ds007172": ["eeg"], "ds007175": ["eeg"], "ds007176": ["eeg"], "ds007180": ["eeg"], "ds007181": ["eeg"], "ds007216": ["eeg"], "ds007221": ["eeg"], "ds007222": ["eeg"], "ds007262": ["eeg"], "ds007314": ["eeg"], "ds007315": ["eeg"], "ds007322": ["eeg"], "ds007338": ["eeg"], "ds007347": ["eeg"], "ds007353": ["eeg", "meg"], "ds007358": ["eeg"], "ds007406": ["eeg"], "ds007427": ["eeg"], "ds007431": ["eeg"], "ds007454": ["eeg"], "ds007471": ["eeg"], "ds007509": ["eeg"], "ds007521": ["eeg"], "ds007526": ["eeg"], "ds007537": ["eeg"], "ds007541": ["eeg"], "ds007554": ["eeg", "nirs"], "ds007558": ["eeg"], "ds007591": ["eeg"], "ds007602": ["eeg"], "ds007605": ["eeg"], "ds007609": ["eeg"], "ds007615": ["eeg"], "ds007629": ["eeg"], "ds007647": ["eeg"], "ds007648": ["eeg"], "ds007655": ["eeg"], "ds007666": ["eeg"], "ds007667": ["eeg"], "ds007688": ["eeg"], "ds007720": ["eeg"], "ds007721": ["eeg"], "ds007788": ["eeg"], "ds007808": ["eeg"], "ds007822": ["eeg"], "ds007823": ["eeg"], "ds007827": ["eeg"], "ds007864": ["eeg"], "ds007865": ["eeg"], "ds002799": ["ieeg"], "ds003029": ["ieeg"], "ds003078": ["ieeg"], "ds003374": ["ieeg"], "ds003498": ["ieeg"], "ds003688": ["ieeg"], "ds003708": ["ieeg"], "ds003844": ["ieeg"], "ds003848": ["ieeg"], "ds003876": ["ieeg"], "ds004100": ["ieeg"], "ds004127": ["ieeg"], "ds004194": ["ieeg"], "ds004080": ["ieeg"], "ds004370": ["ieeg"], "ds004457": ["ieeg"], "ds004473": ["ieeg"], "ds004551": ["ieeg"], "ds004624": ["ieeg"], "ds004642": ["ieeg"], "ds004696": ["ieeg"], "ds004703": ["ieeg"], "ds004770": ["ieeg"], "ds004774": ["ieeg"], "ds004789": ["ieeg"], "ds004809": ["ieeg"], "ds004819": ["ieeg"], "ds004859": ["ieeg"], "ds004865": ["ieeg"], "ds004944": ["ieeg"], "ds004977": ["ieeg"], "ds004993": ["ieeg"], "ds005007": ["ieeg"], "ds005059": ["ieeg"], "ds005083": ["ieeg"], "ds005169": ["ieeg"], "ds005398": ["ieeg"], "ds005411": ["ieeg"], "ds005415": ["ieeg"], "ds005448": ["ieeg"], "ds005489": ["ieeg"], "ds005491": ["ieeg"], "ds005494": ["ieeg"], "ds005522": ["ieeg"], "ds005523": ["ieeg"], "ds005545": ["ieeg"], "ds005557": ["ieeg"], "ds005558": ["ieeg"], "ds005574": ["ieeg"], "ds005592": ["ieeg"], "ds005624": ["ieeg"], "ds005670": ["ieeg"], "ds005691": ["ieeg"], "ds005931": ["ieeg"], "ds005953": ["ieeg"], "ds006065": ["ieeg"], "ds006107": ["ieeg"], "ds006136": ["ieeg"], "ds006233": ["ieeg"], "ds006234": ["ieeg"], "ds006253": ["ieeg"], "ds006392": ["ieeg"], "ds006519": ["ieeg"], "ds006890": ["ieeg"], "ds006910": ["ieeg"], "ds006914": ["ieeg"], "ds007095": ["ieeg"], "ds007118": ["ieeg"], "ds007119": ["ieeg"], "ds007120": ["ieeg"], "ds000248": ["meg"], "ds000117": ["meg"], "ds000246": ["meg"], "ds000247": ["meg"], "ds002001": ["meg"], "ds002312": ["meg"], "ds002550": ["meg"], "ds002712": ["meg"], "ds002761": ["meg"], "ds002885": ["meg"], "ds002908": ["meg"], "ds003082": ["meg"], "ds003104": ["meg"], "ds003352": ["meg"], "ds003392": ["meg"], "ds003483": ["meg"], "ds003568": ["meg"], "ds003633": ["meg"], "ds003682": ["meg"], "ds003694": ["meg"], "ds003703": ["meg"], "ds003922": ["meg"], "ds004011": ["meg"], "ds004012": ["meg"], "ds004078": ["meg"], "ds004107": ["meg"], "ds004212": ["meg"], "ds004229": ["meg"], "ds004276": ["meg"], "ds004278": ["meg"], "ds004330": ["meg"], "ds004346": ["meg"], "ds004398": ["meg"], "ds004483": ["meg"], "ds004738": ["meg"], "ds004837": ["meg"], "ds004998": ["meg"], "ds005065": ["meg"], "ds005107": ["meg"], "ds005241": ["meg"], "ds005261": ["meg"], "ds005279": ["meg"], "ds005346": ["meg"], "ds005356": ["meg"], "ds005752": ["meg"], "ds005810": ["meg"], "ds006012": ["meg"], "ds006035": ["meg"], "ds006334": ["meg"], "ds006468": ["meg"], "ds006502": ["meg"], "ds006629": ["meg"], "ds006720": ["meg"], "ds007523": ["meg"], "ds007524": ["meg"], "ds007640": ["meg"], "ds007663": ["meg"], "ds004830": ["nirs"], "ds004973": ["nirs"], "ds005776": ["nirs"], "ds005777": ["nirs"], "ds005929": ["nirs"], "ds005935": ["nirs"], "ds005963": ["nirs"], "ds005964": ["nirs"], "ds006377": ["nirs"], "ds006459": ["nirs"], "ds006460": ["nirs"], "ds006528": ["nirs"], "ds006545": ["nirs"], "ds006673": ["nirs"], "ds006902": ["nirs"], "ds006903": ["nirs"], "ds007420": ["nirs"], "ds007463": ["nirs"], "ds007473": ["nirs"], "ds007477": ["nirs"], "ds007714": ["nirs"], "ds007719": ["nirs"], "ds007738": ["nirs"]}, "nemar": ["nm000103", "nm000104", "nm000105", "nm000106", "nm000107", "nm000108", "nm000109", "nm000110", "nm000112", "nm000113", "nm000114", "nm000115", "nm000118", "nm000119", "nm000120", "nm000121", "nm000122", "nm000123", "nm000124", "nm000125", "nm000126", "nm000127", "nm000128", "nm000129", "nm000130", "nm000131", "nm000132", "nm000133", "nm000134", "nm000135", "nm000136", "nm000137", "nm000138", "nm000139", "nm000140", "nm000141", "nm000142", "nm000143", "nm000144", "nm000145", "nm000146", "nm000148", "nm000149", "nm000151", "nm000152", "nm000154", "nm000156", "nm000158", "nm000160", "nm000161", "nm000162", "nm000163", "nm000166", "nm000167", "nm000168", "nm000169", "nm000170", "nm000171", "nm000172", "nm000173", "nm000176", "nm000186", "nm000187", "nm000188", "nm000189", "nm000190", "nm000191", "nm000232", "nm000238", "nm000241", "nm000311", "on000117", "on001787", "on002181", "on002578", "on002718", "on002778", "on003190", "on003194", "on003195", "on003343", "on003380", "on003645", "on003800", "on003801", "on003810", "on003825", "on004018", "on004022", "on004362", "on004368", "on004588", "on004661", "on004745", "on004849", "on004850", "on004852", "on004853", "on004854", "on004855", "on005028", "on005261", "on005262", "on005420", "on005505", "on005506", "on005507", "on005508", "on005509", "on005510", "on005511", "on005512", "on005514", "on005515", "on005516", "on005628", "on006126", "on007175", "on007176", "on007180", "on007181", "on007262", "on007315", "on007823", "on007827"]}